srm_helper/__init__.py
srm_helper-0.0.2.dist-info/LICENSE.txt
srm_helper-0.0.2.dist-info/METADATA
srm_helper-0.0.2.dist-info/WHEEL
srm_helper-0.0.2.dist-info/top_level.txt
srm_helper-0.0.2.dist-info/RECORD
